{
  "policy" : {
    "id" : null,
    "name" : "AWS RDS - Elevated CPU Activity (Normal Network Activity)",
    "description" : "Increases in CPU activity are not uncommon when there is a rise in network activity. Increased traffic to a server means more work for that server to do. This policy is designed to catch cases where CPU activity is higher than than normal, and said behavior cannot be explained by a corresponding increase in network traffic. It may or may not represent a problem, but it is useful to know about. ",
    "scope" : {
      "elementName" : "",
      "elementNameExclude" : null,
      "fqnIncludes" : [ ],
      "fqnExcludes" : [ ],
      "elementType" : "RDS",
      "elementTags" : { }
    },
    "duration" : 1800,
    "conditions" : [ {
      "metric" : "aws.rds.networktransmitthroughput",
      "wildcard" : null,
      "metricScopeTags" : { },
      "analytic" : "baselineDeviation",
      "operator" : "undefined",
      "level" : null,
      "level2" : null,
      "metricThresholdLevel" : null,
      "metricThresholdAnalytic" : null
    }, {
      "metric" : "aws.rds.networktransmitthroughput",
      "wildcard" : null,
      "metricScopeTags" : { },
      "analytic" : "contextualDeviation",
      "operator" : "undefined",
      "level" : null,
      "level2" : null,
      "metricThresholdLevel" : null,
      "metricThresholdAnalytic" : null
    }, {
      "metric" : "aws.rds.cpuutilization",
      "wildcard" : null,
      "metricScopeTags" : { },
      "analytic" : "baselineDeviation",
      "operator" : ">",
      "level" : null,
      "level2" : null,
      "metricThresholdLevel" : null,
      "metricThresholdAnalytic" : null
    }, {
      "metric" : "aws.rds.cpuutilization",
      "wildcard" : null,
      "metricScopeTags" : { },
      "analytic" : "contextualDeviation",
      "operator" : ">",
      "level" : null,
      "level2" : null,
      "metricThresholdLevel" : null,
      "metricThresholdAnalytic" : null
    }, {
      "metric" : "aws.rds.networkreceivethroughput",
      "wildcard" : null,
      "metricScopeTags" : { },
      "analytic" : "baselineDeviation",
      "operator" : "undefined",
      "level" : null,
      "level2" : null,
      "metricThresholdLevel" : null,
      "metricThresholdAnalytic" : null
    }, {
      "metric" : "aws.rds.networkreceivethroughput",
      "wildcard" : null,
      "metricScopeTags" : { },
      "analytic" : "contextualDeviation",
      "operator" : "undefined",
      "level" : null,
      "level2" : null,
      "metricThresholdLevel" : null,
      "metricThresholdAnalytic" : null
    } ],
    "eventConditions" : [ ],
    "actions" : [ {
      "type" : "event",
      "category" : 1
    }, {
      "type" : "notification",
      "id" : 23513,
      "enabled" : true
    } ],
    "enabled" : true,
    "deleted" : false,
    "originTenantId" : null,
    "originPolicyId" : null,
    "creatorEmail" : null,
    "lastUpdated" : null
  }
}